anritsu_pwrmtr/__init__.py
anritsu_pwrmtr/common.py
anritsu_pwrmtr/ma243x0a.py
anritsu_pwrmtr/ml243xa.py
anritsu_pwrmtr/version.py
anritsu_pwrmtr-0.1.9.dist-info/LICENSE
anritsu_pwrmtr-0.1.9.dist-info/METADATA
anritsu_pwrmtr-0.1.9.dist-info/WHEEL
anritsu_pwrmtr-0.1.9.dist-info/top_level.txt
anritsu_pwrmtr-0.1.9.dist-info/RECORD
